stmath/__init__.py
stmath/algebra.py
stmath/aptitude_math.py
stmath/benchmark.py
stmath/combinatorics.py
stmath/core.py
stmath/crypto_math.py
stmath/distributions.py
stmath/dl.py
stmath/finance_math.py
stmath/genai.py
stmath/graph.py
stmath/interpreter.py
stmath/math_ext.py
stmath/ml.py
stmath/nlp.py
stmath/number_theory.py
stmath/optimization.py
stmath/probability.py
stmath/quantum_math.py
stmath/scientific.py
stmath/statistics.py
stmath/timeseries.py
stmath/utils.py
stmath/vision.py
stmath-1.0.10.dist-info/licenses/LICENSE
stmath-1.0.10.dist-info/METADATA
stmath-1.0.10.dist-info/WHEEL
stmath-1.0.10.dist-info/top_level.txt
stmath-1.0.10.dist-info/RECORD
