Metadata-Version: 2.4
Name: stmath
Version: 1.0.10
Summary: The Next-Generation Unified Math + AI + ML + Quantum Engine
Home-page: https://github.com/stmath-org/stmath
Author: Saksham Tomar
Author-email: Saksham Tomar <saksham@example.com>
License: MIT
Project-URL: Homepage, https://github.com/stmath-org/stmath
Project-URL: Documentation, https://stmath-org.github.io/docs
Project-URL: Source, https://github.com/stmath-org/stmath
Project-URL: Issues, https://github.com/stmath-org/stmath/issues
Project-URL: PyPI, https://pypi.org/project/stmath/
Project-URL: LinkedIn, https://www.linkedin.com/in/sakshamtomar55/
Keywords: math,ai,ml,quantum,genai,crypto,optimization,vision,stmath
Classifier: Development Status :: 5 - Production/Stable
Classifier: Intended Audience :: Education
Classifier: Intended Audience :: Science/Research
Classifier: License :: OSI Approved :: MIT License
Classifier: Programming Language :: Python :: 3
Classifier: Programming Language :: Python :: 3.8
Classifier: Programming Language :: Python :: 3.9
Classifier: Programming Language :: Python :: 3.10
Classifier: Programming Language :: Python :: 3.11
Classifier: Operating System :: OS Independent
Classifier: Topic :: Scientific/Engineering :: Mathematics
Classifier: Topic :: Software Development :: Libraries :: Python Modules
Requires-Python: >=3.7
License-File: LICENSE
Dynamic: author
Dynamic: license-file
Dynamic: requires-python
